osdan/__init__.py
osdan/custom_tables.py
osdan/data_fetch_methods.py
osdan/date_generators.py
osdan/defaults.py
osdan/downloader.py
osdan/filters.py
osdan/gui.py
osdan/hook-pandas.py
osdan/processing_info_maps.py
osdan/query_wrapers.py
osdan/rows.py
osdan/test_data_fetch_methods.py
osdan/test_date_generators.py
osdan/test_filters.py
osdan/test_performance_stats.py
osdan/test_processing_info_maps.py
osdan/test_query_wrapers.py
osdan/write_file_names.py
osdan-0.0.4.dist-info/METADATA
osdan-0.0.4.dist-info/RECORD
osdan-0.0.4.dist-info/WHEEL
osdan-0.0.4.dist-info/top_level.txt
