Metadata-Version: 2.1
Name: osdan
Version: 0.0.4
Summary: A tool for accessing AEMO data.
Home-page: https://github.com/UNSW-CEEM/osdan
Author: Nicholas Gorman
Author-email: n.gorman305@gmail.com
License: UNKNOWN
Platform: UNKNOWN
Classifier: Programming Language :: Python :: 3
Classifier: License :: OSI Approved :: GNU General Public License (GPL)
Classifier: Operating System :: OS Independent
